<?xml version="1.0" encoding="utf-8"?>
<Produsctos>
  <tipo idTipo="Arma">
    <modelo nombre="pistola">
      <Producto Precio="112" Stock="2" Fecha="2021-01-21T20:33:50.8947437+01:00" />
    </modelo>
    <modelo nombre="metralleta" />
    <modelo nombre="francotirador" />
  </tipo>
  <tipo idTipo="Protecciones">
    <modelo nombre="chaleco" />
    <modelo nombre="casco" />
    <modelo nombre="tanque" />
  </tipo>
  <tipo idTipo="Accesorios">
    <modelo nombre="granada" />
    <modelo nombre="municion" />
    <modelo nombre="cargadores" />
  </tipo>
  <tipo idTipo="coche">
    <modelo nombre="seat" />
  </tipo>
  <tipo idTipo="casa">
    <modelo nombre="trinchera" />
  </tipo>
</Produsctos>